pynmeagps/__init__.py
pynmeagps/_version.py
pynmeagps/exceptions.py
pynmeagps/nmeahelpers.py
pynmeagps/nmeamessage.py
pynmeagps/nmeareader.py
pynmeagps/nmeatypes_core.py
pynmeagps/nmeatypes_decodes.py
pynmeagps/nmeatypes_get.py
pynmeagps/nmeatypes_get_prop.py
pynmeagps/nmeatypes_poll.py
pynmeagps/nmeatypes_poll_prop.py
pynmeagps/nmeatypes_set.py
pynmeagps/nmeatypes_set_prop.py
pynmeagps/socketwrapper.py
pynmeagps-1.0.52.dist-info/licenses/LICENSE
pynmeagps-1.0.52.dist-info/METADATA
pynmeagps-1.0.52.dist-info/WHEEL
pynmeagps-1.0.52.dist-info/top_level.txt
pynmeagps-1.0.52.dist-info/RECORD
